bottle/__init__.py
bottle_sqlalchemy/__init__.py
showergel/__init__.py
showergel/commands/__init__.py
showergel/commands/install.py
showergel/commands/main.py
showergel/commands/serve.py
showergel/commands/version.py
showergel/db.py
showergel/demo.py
showergel/liquidsoap_connector.py
showergel/metadata.py
showergel/rest/__init__.py
showergel/rest/live.py
showergel/rest/metadata_log.py
showergel/rest/schedule.py
showergel/rest/users.py
showergel/scheduler.py
showergel/showergel_bottle.py
showergel/users.py
showergel/version.py
showergel/www/css/app.a379d75e.css
showergel/www/css/chunk-vendors.28f576a3.css
showergel/www/css/playout_history.a95e7105.css
showergel/www/css/schedule.ba45e7ed.css
showergel/www/css/users.18190e52.css
showergel/www/favicon.ico
showergel/www/fonts/materialdesignicons-webfont.147e3378.woff
showergel/www/fonts/materialdesignicons-webfont.174c02fc.ttf
showergel/www/fonts/materialdesignicons-webfont.64d4cf64.eot
showergel/www/fonts/materialdesignicons-webfont.7a44ea19.woff2
showergel/www/index.html
showergel/www/js/about.1db2b40e.js
showergel/www/js/about.1db2b40e.js.map
showergel/www/js/app.b6bfb722.js
showergel/www/js/app.b6bfb722.js.map
showergel/www/js/chunk-vendors.feefe18a.js
showergel/www/js/chunk-vendors.feefe18a.js.map
showergel/www/js/playout_history.c11433f8.js
showergel/www/js/playout_history.c11433f8.js.map
showergel/www/js/playout_history~schedule.8c483731.js
showergel/www/js/playout_history~schedule.8c483731.js.map
showergel/www/js/schedule.db865d79.js
showergel/www/js/schedule.db865d79.js.map
showergel/www/js/users.7b640fc2.js
showergel/www/js/users.7b640fc2.js.map
showergel-0.3.0.dist-info/LICENSE
showergel-0.3.0.dist-info/METADATA
showergel-0.3.0.dist-info/WHEEL
showergel-0.3.0.dist-info/entry_points.txt
showergel-0.3.0.dist-info/RECORD
