Metadata-Version: 2.1
Name: showergel
Version: 0.3.0
Summary: Companion application for a Liquidsoap radio
Home-page: https://github.com/martinkirch/showergel
License: GPL-3.0-only
Keywords: radio,liquidsoap
Author: Martin Kirchgessner
Author-email: martin.kirch@gmail.com
Requires-Python: >=3.7.2,<4.0.0
Classifier: Development Status :: 4 - Beta
Classifier: License :: OSI Approved :: GNU General Public License v3 (GPLv3)
Classifier: Operating System :: POSIX :: Linux
Classifier: Programming Language :: Python :: 3
Classifier: Programming Language :: Python :: 3.8
Classifier: Programming Language :: Python :: 3.9
Classifier: Programming Language :: Python :: 3.10
Classifier: Programming Language :: Python :: 3.11
Classifier: Topic :: Multimedia :: Sound/Audio
Classifier: Topic :: Multimedia :: Sound/Audio :: Players
Requires-Dist: APScheduler (>=3.7.0,<4.0.0)
Requires-Dist: Paste (>=3.5.0,<4.0.0)
Requires-Dist: arrow (>=1.1.0,<2.0.0)
Requires-Dist: click (>=8,<9)
Requires-Dist: sphinx-rtd-theme (>=0.5.1,<0.6.0)
Requires-Dist: sqlalchemy (>=1.3.19,<2.0.0)
Requires-Dist: toml (>=0.10.2,<0.11.0)
Project-URL: Documentation, https://showergel.readthedocs.io/
Project-URL: Repository, https://github.com/martinkirch/showergel.git
